vme.py
vme-0.0.5.dist-info/LICENSE
vme-0.0.5.dist-info/METADATA
vme-0.0.5.dist-info/WHEEL
vme-0.0.5.dist-info/top_level.txt
vme-0.0.5.dist-info/RECORD
