Metadata-Version: 2.1
Name: vme
Version: 0.0.5
Summary: WeChat Work Message Bot.
Author-email: Sun Yijiang <sunyijiang@gmail.com>
Project-URL: Homepage, https://github.com/sunyj/vme
Project-URL: Bug Tracker, https://github.com/sunyj/vme/issues
Classifier: Programming Language :: Python :: 3
Classifier: License :: OSI Approved :: MIT License
Classifier: Operating System :: OS Independent
Requires-Python: >=3.6
License-File: LICENSE
